[
  {
    "_id": "659aabace2615d8332504666",
    "game_event_id": "dd075c2a6d6bd7f7e4dd04261943d09f",
    "date": "2012-08-25T00:00:00.000Z",
    "game_id": 2222597,
    "minute": 80,
    "type": "Goals",
    "club_id": 3725,
    "player_id": 15102,
    "description": ", Right-footed shot, 3. Goal of the Season Assist: , Pass, 1. Assist of the Season",
    "player_assist_id": 51274
  },
  {
    "_id": "659aabace2615d8332504667",
    "game_event_id": "e2488b96b3b03f5e12d1266d10eb1329",
    "date": "2012-08-25T00:00:00.000Z",
    "game_id": 2222597,
    "minute": 40,
    "type": "Cards",
    "club_id": 232,
    "player_id": 19087,
    "description": "3. Yellow card  , Professional foul"
  },
  {
    "_id": "659aabace2615d8332504668",
    "game_event_id": "f946c7d11531cfe4b38730b9e29dde8f",
    "date": "2012-08-25T00:00:00.000Z",
    "game_id": 2222597,
    "minute": 64,
    "type": "Cards",
    "club_id": 232,
    "player_id": 34542,
    "description": "4. Yellow card  , Foul"
  },
  {
    "_id": "659aabace2615d8332504669",
    "game_event_id": "04351ce6486c33ee9ac5ee9f5d28f326",
    "date": "2012-08-25T00:00:00.000Z",
    "game_id": 2222597,
    "minute": 38,
    "type": "Cards",
    "club_id": 3725,
    "player_id": 38005,
    "description": "4. Yellow card  , Professional foul"
  },
  {
    "_id": "659aabace2615d833250466a",
    "game_event_id": "e287cd15540cf6809465ef7db06e5f0b",
    "date": "2012-08-25T00:00:00.000Z",
    "game_id": 2222597,
    "minute": 74,
    "type": "Substitutions",
    "club_id": 3725,
    "player_id": 38005,
    "description": ", Tactical",
    "player_in_id": 158865
  },
  {
    "_id": "659aabace2615d833250466b",
    "game_event_id": "bf8d2d4f2384f5dde17cefaa5993a16d",
    "date": "2012-08-25T00:00:00.000Z",
    "game_id": 2222597,
    "minute": 90,
    "type": "Cards",
    "club_id": 3725,
    "player_id": 42853,
    "description": "2. Yellow card  , Taking of shirt"
  },
  {
    "_id": "659aabace2615d833250466c",
    "game_event_id": "0edf1dcacfd43f2a164311cd550dbfee",
    "date": "2012-08-25T00:00:00.000Z",
    "game_id": 2222597,
    "minute": 90,
    "type": "Goals",
    "club_id": 3725,
    "player_id": 42853,
    "description": ", Header, 1. Goal of the Season Assist: , Corner, 2. Assist of the Season",
    "player_assist_id": 36812
  },
  {
    "_id": "659aabace2615d833250466d",
    "game_event_id": "7dca592c3e9ef6d907ecd6f90a1ff1ae",
    "date": "2012-08-25T00:00:00.000Z",
    "game_id": 2222597,
    "minute": 20,
    "type": "Substitutions",
    "club_id": 232,
    "player_id": 45593,
    "description": ", Injury",
    "player_in_id": 120630
  },
  {
    "_id": "659aabace2615d833250466e",
    "game_event_id": "8737dc3c-84c3-484c-8256-5953a0834eae",
    "date": "2012-08-25T00:00:00.000Z",
    "game_id": 2222597,
    "minute": 75,
    "type": "Substitutions",
    "club_id": 232,
    "player_id": 48067,
    "description": ", Tactical",
    "player_in_id": 38539
  },
  {
    "_id": "659aabace2615d833250466f",
    "game_event_id": "711bbe326e403b169f58085834e3191b",
    "date": "2012-08-25T00:00:00.000Z",
    "game_id": 2222597,
    "minute": 64,
    "type": "Substitutions",
    "club_id": 3725,
    "player_id": 48634,
    "description": ", Tactical",
    "player_in_id": 26082
  },
  {
    "_id": "659aabace2615d8332504670",
    "game_event_id": "870091aabc6e97aa25640b367eb438c7",
    "date": "2012-08-25T00:00:00.000Z",
    "game_id": 2222597,
    "minute": 72,
    "type": "Substitutions",
    "club_id": 3725,
    "player_id": 53286,
    "description": ", Tactical",
    "player_in_id": 51268
  },
  {
    "_id": "659aabace2615d8332504671",
    "game_event_id": "d527434a0fbe83f53b09391d73c44326",
    "date": "2012-08-25T00:00:00.000Z",
    "game_id": 2222597,
    "minute": 51,
    "type": "Cards",
    "club_id": 232,
    "player_id": 63149,
    "description": "3. Yellow card  , Foul"
  },
  {
    "_id": "659aabace2615d8332504672",
    "game_event_id": "f5788349b4edfb151d07e3d1c20c9190",
    "date": "2012-08-25T00:00:00.000Z",
    "game_id": 2222597,
    "minute": 65,
    "type": "Goals",
    "club_id": 232,
    "player_id": 65072,
    "description": ", Header, 1. Goal of the Season Assist: , Corner, 1. Assist of the Season",
    "player_assist_id": 105496
  },
  {
    "_id": "659aabace2615d8332504673",
    "game_event_id": "cce51b66f955dc7fe42835304b2f42de",
    "date": "2012-08-25T00:00:00.000Z",
    "game_id": 2222597,
    "minute": 79,
    "type": "Substitutions",
    "club_id": 232,
    "player_id": 105496,
    "description": ", Tactical",
    "player_in_id": 63170
  }
]
